webdrivers/__init__.py
webdrivers/cli.py
webdrivers/webdrivers.py
tchappui_webdrivers-0.3.7.dist-info/AUTHORS.rst
tchappui_webdrivers-0.3.7.dist-info/LICENSE
tchappui_webdrivers-0.3.7.dist-info/METADATA
tchappui_webdrivers-0.3.7.dist-info/WHEEL
tchappui_webdrivers-0.3.7.dist-info/entry_points.txt
tchappui_webdrivers-0.3.7.dist-info/top_level.txt
tchappui_webdrivers-0.3.7.dist-info/RECORD
