Metadata-Version: 2.1
Name: tchappui-webdrivers
Version: 0.3.7
Summary: Script to install the latest versions of chromedriver and geckodriver on travis
Home-page: https://github.com/pythonmentor/tchappui-webdrivers
Author: Thierry Chappuis
Author-email: tchappui@gmail.com
License: MIT license
Keywords: geckodriver,chromedriver
Platform: UNKNOWN
Classifier: Development Status :: 2 - Pre-Alpha
Classifier: Intended Audience :: Developers
Classifier: License :: OSI Approved :: MIT License
Classifier: Natural Language :: English
Classifier: Programming Language :: Python :: 3
Classifier: Programming Language :: Python :: 3.5
Classifier: Programming Language :: Python :: 3.6
Classifier: Programming Language :: Python :: 3.7
Classifier: Programming Language :: Python :: 3.8
Requires-Python: >=3.5
Requires-Dist: Click (>=7.0)
Requires-Dist: requests
